README
bottle_memcache.py
setup.py
bottle_memcache.egg-info/PKG-INFO
bottle_memcache.egg-info/SOURCES.txt
bottle_memcache.egg-info/dependency_links.txt
bottle_memcache.egg-info/not-zip-safe
bottle_memcache.egg-info/requires.txt
bottle_memcache.egg-info/top_level.txt