Metadata-Version: 1.1
Name: bottle-memcache
Version: 0.2.1
Summary: Memcache integration for Bottle.
Home-page: http://github.com/bottlepy/bottle-extras/
Author: Jorge Gallegos
Author-email: kad@blegh.net
License: MIT
Platform: any
Classifier: Environment :: Web Environment
Classifier: Intended Audience :: Developers
Classifier: License :: OSI Approved :: MIT License
Classifier: Operating System :: OS Independent
Classifier: Programming Language :: Python
Classifier: Topic :: Internet :: WWW/HTTP :: Dynamic Content
Classifier: Topic :: Software Development :: Libraries :: Python Modules
